[
	{
    "id": "mon_carnufex",
	"type": "MONSTER",
    "name": { "str_sp": "carnufex" },
    "description": "WIP",
	"volume": "150 L",
    "weight": "150 kg",
	"default_faction": "touhou_crocodylomorpha_large",
    "bodytype": "bear",
    "categories": [ "WILDLIFE" ],
	"species": [ "REPTILE" ],
    "harvest": "reptile_large_leather",
    "hp": 115,
    "speed": 145,
    "material": [ "flesh" ],
	"symbol": "ċ",
    "looks_like": "mon_gator",
	"color": "dark_gray_green",
    "aggression": 25,
    "morale": 50,
    "melee_skill": 6,
    "melee_dice": 3,
    "melee_dice_sides": 6,
    "melee_cut": 6,
    "dodge": 4,
    "armor_bash": 4,
    "armor_cut": 6,
    "armor_stab": 2,
    "armor_bullet": 6,
	"vision_night": 5,
	"path_settings": { "max_dist": 10 },
	"reproduction": { "baby_egg": "egg_carnufex", "baby_count": 10, "baby_timer": 30 },
    "baby_flags": [ "SPRING", "SUMMER", "AUTUMN", "WINTER" ],
    "anger_triggers": [ "FRIEND_ATTACKED", "FRIEND_DIED", "PLAYER_WEAK", "HURT" ],
    "placate_triggers": [ "MEAT" ],
	"special_attacks": [ [ "EAT_FOOD", 80 ], [ "GRAB", 20 ] ],
    "flags": [ "ANIMAL", "HEARS", "PATH_AVOID_DANGER_1", "SEES", "SMELLS", "WARM" ],
	"//": "Based on Carnufex sp.. No reproductive data"
	},
	{
    "id": "mon_carnufex_baby",
    "type": "MONSTER",
    "name": { "str": "baby carnufex", "str_pl": "baby carnufex" },
    "copy-from": "mon_carnufex",
	"description": "WIP",
    "volume": "10 L",
    "weight": "10 kg",
	"hp": 35,
    "speed": 125,
	"color": "dark_gray",
    "morale": 25,
	"melee_skill": 4,
	"melee_dice": 3,
    "melee_dice_sides": 4,
    "melee_cut": 6,
    "armor_bash": 2,
    "armor_cut": 2,
    "armor_stab": 0,
    "armor_bullet": 2,
	"upgrades": { "age_grow": 30, "into": "mon_carnufex" },
    "special_attacks": [ [ "EAT_FOOD", 50 ] ],
    "extend": { "flags": [ "NO_BREED" ] }
	},
	{
    "id": "mon_ichthyosaurus",
    "type": "MONSTER",
    "name": { "str": "ichthyosaurus", "str_pl": "ichthyosaurus" },
    "description": "An animal you could mistake for a dolphin if it wasn't for some key differences.  The first one are the eyes, huge, piercing eyes coverered by sclerotic rings you feel are tracking several things at once, you included.  The second are the serrated jaws, reminding you of crocodiles and the stereotypical dinosaur.  The third are the fins, with the caudal fin being vertical, and the dorsal fin being somewhat small.",
    "volume": "165 L",
    "weight": "165 kg",
	"default_faction": "touhou_reptile_marine_large",
    "bodytype": "fish",
    "categories": [ "WILDLIFE" ],
    "species": [ "REPTILE" ],
    "harvest": "reptile_marine_harvest",
	"hp": 175,
    "speed": 150,
	"material": [ "flesh" ],
	"color": "light_blue",
	"symbol": "I",
    "aggression": 15,
    "morale": 25,
	"melee_skill": 4,
	"melee_dice": 2,
    "melee_dice_sides": 6,
    "melee_cut": 6,
	"dodge": 2,
    "armor_bash": 2,
	"armor_cut": 3,
	"armor_stab": 4,
	"reproduction": { "baby_monster": "mon_ichthyosaurus_baby", "baby_count": 1, "baby_timer": 20 },
    "baby_flags": [ "SPRING", "SUMMER", "AUTUMN", "WINTER" ],
    "anger_triggers": [ "HURT", "FRIEND_ATTACKED", "PLAYER_NEAR_BABY" ],
	"fear_triggers": [ "FRIEND_DIED" ],
    "special_attacks": [ [ "EAT_FOOD", 100 ], [ "PARROT", 12 ] ],
	"flags": [ "ANIMAL", "AQUATIC", "SEES", "SMELLS", "SWIMS", "WATER_CAMOUFLAGE" ],
    "//": "Ichthyosaurus communis used as reference. Don't know if they had vocalizations but that's how I imagine them to be",
	"//2": "Coprolites include fish and squid, and the big characteristic eyes indicate it could hunt in low light conditions, with great depths included"
	},
	{
    "id": "mon_ichthyosaurus_baby",
    "type": "MONSTER",
    "name": { "str": "baby ichthyosaurus", "str_pl": "baby ichthyosaurus" },
    "copy-from": "mon_ichthyosaurus",
	"description": "A smaller Ichthyosaurus, this would be a curious animal to keep in a big fish tank in the hall, if you were the side villain of a movie.",
    "volume": "5 L",
    "weight": "5 kg",
	"hp": 55,
    "speed": 125,
	"color": "blue",
    "aggression": 10,
    "morale": 15,
	"melee_skill": 4,
	"melee_dice": 2,
    "melee_dice_sides": 3,
    "melee_cut": 5,
	"dodge": 3,
    "armor_bash": 1,
	"armor_cut": 2,
	"armor_stab": 2,
	"upgrades": { "age_grow": 24, "into": "mon_ichthyosaurus" },
    "special_attacks": [ [ "EAT_FOOD", 80 ], [ "PARROT", 24 ] ],
    "extend": { "flags": [ "NO_BREED" ] }
	},
	{
    "id": "mon_plesiosaurus",
    "type": "MONSTER",
    "name": { "str": "plesiosaurus", "str_pl": "plesiosaurus" },
    "description": "An animal that looks like certain Scottish cryptid.  It has a characteristic long neck with a small head.  The animal paddles through water as it moves its head side to side to catch fish.  The overall aspect and size are somewhat disappointing.",
    "volume": "150 L",
    "weight": "150 kg",
	"default_faction": "touhou_reptile_marine_large",
    "bodytype": "fish",
    "categories": [ "WILDLIFE" ],
    "species": [ "REPTILE" ],
    "harvest": "reptile_marine_harvest",
	"hp": 145,
    "speed": 125,
	"material": [ "flesh" ],
	"color": "light_gray",
	"symbol": "J",
    "aggression": 15,
    "morale": 20,
	"melee_skill": 3,
	"melee_dice": 2,
    "melee_dice_sides": 7,
    "melee_cut": 6,
	"dodge": 2,
    "armor_bash": 2,
	"armor_cut": 3,
	"armor_stab": 2,
	"reproduction": { "baby_monster": "mon_plesiosaurus_baby", "baby_count": 1, "baby_timer": 20 },
    "baby_flags": [ "SPRING", "SUMMER", "AUTUMN", "WINTER" ],
    "anger_triggers": [ "HURT", "PLAYER_NEAR_BABY" ],
	"fear_triggers": [ "FRIEND_DIED" ],
    "special_attacks": [ [ "EAT_FOOD", 35 ] ],
	"flags": [ "ANIMAL", "AQUATIC", "SEES", "SMELLS", "SWIMS", "WATER_CAMOUFLAGE" ],
    "//": "Plesiosaurus dolichodeirus used as reference, Plesiosaurus is a wastebasket taxon"
	},
	{
    "id": "mon_plesiosaurus_baby",
    "type": "MONSTER",
    "name": { "str": "baby plesiosaurus", "str_pl": "baby plesiosaurus" },
    "copy-from": "mon_plesiosaurus",
	"description": "A small Nessie.",
    "volume": "3500 ml",
    "weight": "3000 g",
	"hp": 40,
    "speed": 115,
	"color": "light_blue",
    "aggression": 10,
    "morale": 15,
	"melee_skill": 3,
	"melee_dice": 2,
    "melee_dice_sides": 5,
    "melee_cut": 3,
	"dodge": 3,
    "armor_bash": 1,
	"armor_cut": 1,
	"armor_stab": 1,
	"upgrades": { "age_grow": 20, "into": "mon_plesiosaurus" },
    "special_attacks": [ [ "EAT_FOOD", 25 ] ],
    "extend": { "flags": [ "NO_BREED" ] }
	}
]
