[
	{
    "id": "spell_components_blacksun",
    "type": "requirement",
    "components": [ [ [ "utsuho_sun2", 1 ] ] ]
	},
	{
    "id": "spell_components_gungnir",
    "type": "requirement",
    "components": [ [ [ "remilia_gungnir2", 1 ] ] ]
	},
	{
    "id": "spell_components_humanegg20",
    "type": "requirement",
    "components": [ [ [ "human_egg", 20 ] ] ]
	},
	{
    "id": "spell_components_ikuscarf",
    "type": "requirement",
    "tools": [ [ [ "iku_long_scarf", -1 ] ], [ [ "iku_long_scarf_loose", -1 ] ] ]
	},
	{
    "id": "spell_components_jian",
    "type": "requirement",
    "tools": [ [ [ "tenshi_jian_extended", -1 ] ] ]
	},
	{
    "id": "spell_components_keystone",
    "type": "requirement",
    "components": [ [ [ "tenko_keystone2", 1 ] ] ]
	}
]